pycheevos/__init__.py
pycheevos/core/condition.py
pycheevos/core/constants.py
pycheevos/core/helpers.py
pycheevos/core/value.py
pycheevos/models/achievement.py
pycheevos/models/generic.py
pycheevos/models/leaderboard.py
pycheevos/models/rich_presence.py
pycheevos/models/set.py
pycheevos/utils/import_achievements.py
pycheevos/utils/import_leaderboard.py
pycheevos/utils/import_notes.py
pycheevos/utils/import_set.py
pycheevos/utils/importer.py
pycheevos/utils/sync.py
pycheevos-0.0.6.dist-info/licenses/LICENSE
pycheevos-0.0.6.dist-info/METADATA
pycheevos-0.0.6.dist-info/WHEEL
pycheevos-0.0.6.dist-info/entry_points.txt
pycheevos-0.0.6.dist-info/top_level.txt
pycheevos-0.0.6.dist-info/RECORD
