Metadata-Version: 2.4
Name: pycheevos
Version: 0.0.6
Summary: A Python library to generate RetroAchievements scripts programmatically.
Author: Carlos Natanael, Player1041
License: This is free and unencumbered software released into the public domain.
Project-URL: Homepage, https://github.com/CarlosNatanael/PyCheevos
Project-URL: Bug Tracker, https://github.com/CarlosNatanael/PyCheevos/issues
Keywords: retroachievements,achievements,generator,emulator,ratools
Classifier: Programming Language :: Python :: 3
Classifier: License :: OSI Approved :: MIT License
Classifier: Operating System :: OS Independent
Classifier: Topic :: Games/Entertainment
Classifier: Topic :: Software Development :: Libraries :: Python Modules
Requires-Python: >=3.7
License-File: LICENSE
Dynamic: license-file
